{
  "project_info": {
    "project_number": "584362757991",
    "firebase_url": "https://intern-tracker-8bb5a-default-rtdb.firebaseio.com",
    "project_id": "intern-tracker-8bb5a",
    "storage_bucket": "intern-tracker-8bb5a.firebasestorage.app"
  },
  "client": [
    {
      "client_info": {
        "mobilesdk_app_id": "1:584362757991:android:e51819b7a7ae5cce0929c2",
        "android_client_info": {
          "package_name": "com.example.flutter_application_2"
        }
      },
      "oauth_client": [
        {
          "client_id": "584362757991-e22g7vef7lu7mggmfjbgamq4n972umeq.apps.googleusercontent.com",
          "client_type": 1,
          "android_info": {
            "package_name": "com.example.flutter_application_2",
            "certificate_hash": "a66383d95b19ecae884069752a895e4b06dbf289"
          }
        },
        {
          "client_id": "584362757991-k15o3r8hala88uvlc2ml3m67eirhk4n4.apps.googleusercontent.com",
          "client_type": 3
        }
      ],
      "api_key": [
        {
          "current_key": "AIzaSyBVchMWuqLokzsS3tLhwbePnXSQ032QyCc"
        }
      ],
      "services": {
        "appinvite_service": {
          "other_platform_oauth_client": [
            {
              "client_id": "584362757991-k15o3r8hala88uvlc2ml3m67eirhk4n4.apps.googleusercontent.com",
              "client_type": 3
            },
            {
              "client_id": "584362757991-8lmfojphnfuum6b8v6u3kui2uua0ffcc.apps.googleusercontent.com",
              "client_type": 2,
              "ios_info": {
                "bundle_id": "com.example.flutterApplication2"
              }
            }
          ]
        }
      }
    },
    {
      "client_info": {
        "mobilesdk_app_id": "1:584362757991:android:e151d52d695ccdda0929c2",
        "android_client_info": {
          "package_name": "com.example.interntracker_admin"
        }
      },
      "oauth_client": [
        {
          "client_id": "584362757991-k15o3r8hala88uvlc2ml3m67eirhk4n4.apps.googleusercontent.com",
          "client_type": 3
        }
      ],
      "api_key": [
        {
          "current_key": "AIzaSyBVchMWuqLokzsS3tLhwbePnXSQ032QyCc"
        }
      ],
      "services": {
        "appinvite_service": {
          "other_platform_oauth_client": [
            {
              "client_id": "584362757991-k15o3r8hala88uvlc2ml3m67eirhk4n4.apps.googleusercontent.com",
              "client_type": 3
            },
            {
              "client_id": "584362757991-8lmfojphnfuum6b8v6u3kui2uua0ffcc.apps.googleusercontent.com",
              "client_type": 2,
              "ios_info": {
                "bundle_id": "com.example.flutterApplication2"
              }
            }
          ]
        }
      }
    }
  ],
  "configuration_version": "1"
}